pyfilemaster/__init__.py
pyfilemaster/main.py
pyfilemaster-0.1.8.dist-info/LICENSE
pyfilemaster-0.1.8.dist-info/METADATA
pyfilemaster-0.1.8.dist-info/WHEEL
pyfilemaster-0.1.8.dist-info/top_level.txt
pyfilemaster-0.1.8.dist-info/RECORD
