Metadata-Version: 2.1
Name: pyfilemaster
Version: 0.1.8
Summary: A Python package for file handling utilities
Home-page: https://github.com/Shubhashish-Chakraborty/pyfilemaster
Author: beingshubh (Shubhashish Chakraborty)
Author-email: shubhashish147@gmail.com
License: MIT
Keywords: pyfilemaster,pyfilemaster pypi,pyfilemaster github,file handling,binary to CSV,binary,csv,text,excel,dat,file conversion,pyfilemaster python,pyfilemaster python package
Classifier: Programming Language :: Python :: 3
Classifier: License :: OSI Approved :: MIT License
Classifier: Operating System :: OS Independent
Requires-Python: >=3.6
License-File: LICENSE
